_esbuild.cpython-312-x86_64-linux-musl.h
_esbuild.cpython-312-x86_64-linux-musl.so
esbuild_py/__init__.py
esbuild_py/esbuild.py
esbuild_py-0.1.6.dist-info/METADATA
esbuild_py-0.1.6.dist-info/WHEEL
esbuild_py-0.1.6.dist-info/top_level.txt
esbuild_py-0.1.6.dist-info/RECORD
esbuild_py-0.1.6.dist-info/licenses/LICENSE
