Metadata-Version: 2.1
Name: esbuild_py
Version: 0.1.6
Summary: Python bindings to the esbuild Transform API
Author-email: Mark Keller <mark_keller@hms.harvard.edu>
License: MIT License
Project-URL: repository, https://github.com/keller-mark/esbuild-py
Keywords: widgets,javascript,react
Classifier: Development Status :: 4 - Beta
Classifier: Framework :: IPython
Classifier: Intended Audience :: Developers
Classifier: Programming Language :: Python :: 3.7
Classifier: Programming Language :: Python :: 3.8
Classifier: Programming Language :: Python :: 3.9
Classifier: Programming Language :: Python :: 3.10
Classifier: Programming Language :: Python :: 3.11
Classifier: Programming Language :: Python :: 3.12
Requires-Python: >=3.7
License-File: LICENSE
Provides-Extra: dev
Requires-Dist: build==0.1.0; extra == "dev"
Requires-Dist: pytest>=6.2.4; extra == "dev"
Requires-Dist: coverage>=6.3.2; extra == "dev"
Requires-Dist: flake8==3.8.4; extra == "dev"
